README.rst
setup.py
django_viewmodels.egg-info/PKG-INFO
django_viewmodels.egg-info/SOURCES.txt
django_viewmodels.egg-info/dependency_links.txt
django_viewmodels.egg-info/not-zip-safe
django_viewmodels.egg-info/top_level.txt
djviewmodels/__init__.py
djviewmodels/decorators.py
djviewmodels/models.py
djviewmodels/test_views.py
djviewmodels/tests.py
djviewmodels/utils.py
djviewmodels/viewmodels.py
djviewmodels/views.py