Metadata-Version: 1.1
Name: django-viewmodels
Version: 0.3.7
Summary: Class based views for Django with automatic viewmodel rendering
Home-page: UNKNOWN
Author: Jeff Schwaber, Chris Pitzer, LoFi Art
Author-email: freyley@gmail.com
License: UNKNOWN
Platform: UNKNOWN
Classifier: Development Status :: 3 - Alpha
Classifier: Environment :: Web Environment
Classifier: Intended Audience :: Developers
Classifier: License :: OSI Approved :: BSD License
Classifier: Operating System :: OS Independent
Classifier: Programming Language :: Python
Classifier: Framework :: Django
